webclipper/__init__.py
webclipper/main.py
webclipper-0.2.0.dist-info/METADATA
webclipper-0.2.0.dist-info/WHEEL
webclipper-0.2.0.dist-info/entry_points.txt
webclipper-0.2.0.dist-info/top_level.txt
webclipper-0.2.0.dist-info/RECORD
