Metadata-Version: 2.4
Name: webclipper
Version: 0.2.0
Summary: A tool to fetch the main content of a webpage and convert it to Markdown or plain text.
Author-email: Hugo Martiniano <hugomartiniano@gmail.com>
Project-URL: Homepage, https://github.com/hmartiniano/webclipper
Classifier: Programming Language :: Python :: 3
Classifier: License :: OSI Approved :: MIT License
Classifier: Operating System :: OS Independent
Requires-Python: >=3.8
Requires-Dist: requests
Requires-Dist: beautifulsoup4
Requires-Dist: html2text
Requires-Dist: readability-lxml
